[
{
  "image": {
    "name": "./api/tmp/34b87a78cb75d52533016cd6914f016f/Rectangle%2012.png",
    "format": "PNG",
    "formatDescription": "Portable Network Graphics",
    "mimeType": "image/png",
    "class": "DirectClass",
    "geometry": {
      "width": 104,
      "height": 21,
      "x": 0,
      "y": 0
    },
    "resolution": {
      "x": 28.35,
      "y": 28.35
    },
    "printSize": {
      "x": 3.66843,
      "y": 0.740741
    },
    "units": "PixelsPerCentimeter",
    "type": "PaletteAlpha",
    "endianess": "Undefined",
    "colorspace": "sRGB",
    "depth": 8,
    "baseDepth": 8,
    "channelDepth": {
      "alpha": 8,
      "red": 8,
      "green": 8,
      "blue": 8
    },
    "pixels": 2184,
    "imageStatistics": {
      "all": {
        "min": 0,
        "max": 255,
        "mean": 205.296,
        "standardDeviation": 4689.94,
        "kurtosis": 6.42286,
        "skewness": -0.754864,
        "entropy": 0.145984
      }
    },
    "channelStatistics": {
      "alpha": {
        "min": 255,
        "max": 0,
        "mean": 2.54075,
        "standardDeviation": 5803.25,
        "kurtosis": 97.9794,
        "skewness": -9.74609,
        "entropy": 0.0500437
      },
      "red": {
        "min": 0,
        "max": 196,
        "mean": 191.813,
        "standardDeviation": 4389.23,
        "kurtosis": 85.947,
        "skewness": -8.31398,
        "entropy": 0.156729
      },
      "green": {
        "min": 0,
        "max": 202,
        "mean": 197.597,
        "standardDeviation": 4557.36,
        "kurtosis": 83.2948,
        "skewness": -8.15491,
        "entropy": 0.193764
      },
      "blue": {
        "min": 0,
        "max": 183,
        "mean": 179.316,
        "standardDeviation": 4009.93,
        "kurtosis": 94.0834,
        "skewness": -8.78685,
        "entropy": 0.183398
      }
    },
    "alpha": "#00000000",
    "renderingIntent": "Perceptual",
    "gamma": 0.45455,
    "chromaticity": {
      "redPrimary": {
        "x": 0.64,
        "y": 0.33
      },
      "greenPrimary": {
        "x": 0.3,
        "y": 0.6
      },
      "bluePrimary": {
        "x": 0.15,
        "y": 0.06
      },
      "whitePrimary": {
        "x": 0.3127,
        "y": 0.329
      }
    },
    "backgroundColor": "#FFFFFFFF",
    "borderColor": "#DFDFDFFF",
    "matteColor": "#BDBDBDFF",
    "transparentColor": "#00000000",
    "interlace": "None",
    "intensity": "Undefined",
    "compose": "Over",
    "pageGeometry": {
      "width": 104,
      "height": 21,
      "x": 0,
      "y": 0
    },
    "dispose": "Undefined",
    "iterations": 0,
    "compression": "Zip",
    "orientation": "Undefined",
    "properties": {
      "date:create": "2021-05-07T16:09:38+00:00",
      "date:modify": "2021-05-07T16:09:38+00:00",
      "png:cHRM": "chunk was found (see Chromaticity, above)",
      "png:gAMA": "gamma=0.45455 (See Gamma, above)",
      "png:IHDR.bit-depth-orig": "8",
      "png:IHDR.bit_depth": "8",
      "png:IHDR.color-type-orig": "6",
      "png:IHDR.color_type": "6 (RGBA)",
      "png:IHDR.interlace_method": "0 (Not interlaced)",
      "png:IHDR.width,height": "104, 21",
      "png:pHYs": "x_res=2835, y_res=2835, units=1",
      "png:sRGB": "intent=0 (Perceptual Intent)",
      "signature": "03b1d1ba6a146799da6a051bd1a7d90761cd326dcee4b82b2bddf1a0c916e6a8"
    },
    "artifacts": {
      "filename": "./api/tmp/34b87a78cb75d52533016cd6914f016f/Rectangle%2012.png"
    },
    "tainted": false,
    "filesize": "0B",
    "numberPixels": "2184",
    "pixelsPerSecond": "3.22133MB",
    "userTime": "0.000u",
    "elapsedTime": "0:01.000",
    "version": "ImageMagick 6.9.10-86 Q16 x86_64 2020-01-13 https://imagemagick.org"
  }
}
]